odoo10_addon_hr_employee_data_from_work_address-10.0.1.0.0.99.dev3-py3.8-nspkg.pth
odoo/addons/hr_employee_data_from_work_address/README.rst
odoo/addons/hr_employee_data_from_work_address/__init__.py
odoo/addons/hr_employee_data_from_work_address/__manifest__.py
odoo/addons/hr_employee_data_from_work_address/init_hook.py
odoo/addons/hr_employee_data_from_work_address/data/res_partner_category.xml
odoo/addons/hr_employee_data_from_work_address/i18n/ar.po
odoo/addons/hr_employee_data_from_work_address/i18n/de.po
odoo/addons/hr_employee_data_from_work_address/i18n/es.po
odoo/addons/hr_employee_data_from_work_address/i18n/fi.po
odoo/addons/hr_employee_data_from_work_address/i18n/fr.po
odoo/addons/hr_employee_data_from_work_address/i18n/hr_employee_data_from_work_address.pot
odoo/addons/hr_employee_data_from_work_address/i18n/it.po
odoo/addons/hr_employee_data_from_work_address/i18n/pt_BR.po
odoo/addons/hr_employee_data_from_work_address/i18n/ro.po
odoo/addons/hr_employee_data_from_work_address/i18n/sl.po
odoo/addons/hr_employee_data_from_work_address/models/__init__.py
odoo/addons/hr_employee_data_from_work_address/models/hr_employee.py
odoo/addons/hr_employee_data_from_work_address/readme/CONTRIBUTORS.rst
odoo/addons/hr_employee_data_from_work_address/readme/CREDITS.rst
odoo/addons/hr_employee_data_from_work_address/readme/DESCRIPTION.rst
odoo/addons/hr_employee_data_from_work_address/readme/USAGE.rst
odoo/addons/hr_employee_data_from_work_address/static/description/icon.png
odoo/addons/hr_employee_data_from_work_address/static/description/index.html
odoo/addons/hr_employee_data_from_work_address/tests/__init__.py
odoo/addons/hr_employee_data_from_work_address/tests/test_hr_employee_data_from_work_address.py
odoo/addons/hr_employee_data_from_work_address/views/hr_employee.xml
odoo/addons/hr_employee_data_from_work_address/views/res_users.xml
odoo10_addon_hr_employee_data_from_work_address-10.0.1.0.0.99.dev3.dist-info/METADATA
odoo10_addon_hr_employee_data_from_work_address-10.0.1.0.0.99.dev3.dist-info/WHEEL
odoo10_addon_hr_employee_data_from_work_address-10.0.1.0.0.99.dev3.dist-info/namespace_packages.txt
odoo10_addon_hr_employee_data_from_work_address-10.0.1.0.0.99.dev3.dist-info/top_level.txt
odoo10_addon_hr_employee_data_from_work_address-10.0.1.0.0.99.dev3.dist-info/RECORD
