Metadata-Version: 2.1
Name: odoo10-addon-hr-employee-data-from-work-address
Version: 10.0.1.0.0.99.dev3
Summary: Update user's and partner's data fields from employee record
Home-page: https://github.com/OCA/hr
Author: Odoo Community Association (OCA),Therp BV
Author-email: support@odoo-community.org
License: AGPL-3
Platform: UNKNOWN
Classifier: Programming Language :: Python
Classifier: Framework :: Odoo
Classifier: Framework :: Odoo :: 10.0
Classifier: License :: OSI Approved :: GNU Affero General Public License v3
Requires-Python: ~=2.7
Requires-Dist: odoo <10.1dev,>=10.0
